passthon/__init__.py
passthon/passthon.py
passthon/test.py
passthon-0.0.1.dist-info/METADATA
passthon-0.0.1.dist-info/WHEEL
passthon-0.0.1.dist-info/top_level.txt
passthon-0.0.1.dist-info/RECORD
