Metadata-Version: 2.1
Name: passthon
Version: 0.0.1
Summary: Library for generating random passwords
Home-page: https://github.com/fckingadrien
Author: Adrián Fernández
Author-email: 48542598+fckingadrien@users.noreply.github.com
License: MIT
Platform: UNKNOWN
